messengerapi/__init__.py
messengerapi/attachment_upload_api.py
messengerapi/components.py
messengerapi/messenger_profile_api.py
messengerapi/send_api.py
messenger_api_python-2022.4.22.dist-info/LICENSE
messenger_api_python-2022.4.22.dist-info/METADATA
messenger_api_python-2022.4.22.dist-info/WHEEL
messenger_api_python-2022.4.22.dist-info/top_level.txt
messenger_api_python-2022.4.22.dist-info/RECORD
