Metadata-Version: 2.1
Name: messenger-api-python
Version: 2022.4.22
Summary: Python wrapper to the various APIs in Facebook Messenger Platform
Home-page: https://github.com/krishna2206/messenger-api-python
Author: krishna2206
Author-email: fitiavana.krishna@gmail.com
License: MIT License
Platform: UNKNOWN
Classifier: Programming Language :: Python :: 3.7
Classifier: License :: OSI Approved :: MIT License
Classifier: Operating System :: OS Independent
Requires-Python: >=3.7
License-File: LICENSE
Requires-Dist: python-magic (==0.4.25)
Requires-Dist: requests (==2.26.0)
Requires-Dist: requests-toolbelt (==0.9.1)
